async_regigen/__init__.py
async_regigen/geometry.py
async_regigen-0.1.1.dist-info/licenses/LICENSE
async_regigen-0.1.1.dist-info/METADATA
async_regigen-0.1.1.dist-info/WHEEL
async_regigen-0.1.1.dist-info/top_level.txt
async_regigen-0.1.1.dist-info/RECORD
