Metadata-Version: 2.4
Name: async_regigen
Version: 0.1.1
Summary: A async utility package for generating coordinates of rotated geometric shapes.
Author-email: "houqi.li" <lihouqi007@gmail.com>
License: MIT
Keywords: geometry,rotation,rectangle,util
Classifier: Programming Language :: Python :: 3
Classifier: License :: OSI Approved :: MIT License
Classifier: Operating System :: OS Independent
Classifier: Topic :: Scientific/Engineering :: Mathematics
Requires-Python: >=3.8
License-File: LICENSE
Requires-Dist: shapely>=2.0.0
Dynamic: license-file
